{
    "encript": {
        "first": {
            "A": ".",
            "B": ",",
            "C": "/",
            "D": "C",
            "E": "8",
            "F": "9",
            "G": "5",
            "H": "E",
            "I": "0",
            "J": "4",
            "K": "3",
            "L": "A",
            "M": "B",
            "N": "S",
            "O": "Q",
            "P": "Z",
            "R": "|",
            "S": "[",
            "T": "]",
            "U": "{",
            "V": "}",
            "W": "?",
            "X": ":",
            "Y": ";",
            "Z": ">",
            " ": "2"
        },
        "second": {
            ".": ",",
            ",": ":",
            "/": "}",
            "C": "{",
            "8": "]",
            "9": "[",
            "5": ".",
            "E": "_",
            "0": "-",
            "4": "=",
            "3": "+",
            "A": "(",
            "B": ")",
            "S": "&",
            "Q": "%",
            "Z": "$",
            "|": "#",
            "[": "@",
            "]": "!",
            "{": "/",
            "}": "<",
            "?": ">",
            ":": ";",
            ";": "|",
            ">": "*",
            "2": "9"
        }
    },
    "decript": {
        "first": {
            ".": "A",
            ",": "B",
            "/": "C",
            "C": "D",
            "8": "E",
            "9": "F",
            "5": "G",
            "E": "H",
            "0": "I",
            "4": "J",
            "3": "K",
            "A": "L",
            "B": "M",
            "S": "N",
            "Q": "O",
            "Z": "P",
            "|": "R",
            "[": "S",
            "]": "T",
            "{": "U",
            "}": "V",
            "?": "W",
            ":": "X",
            ";": "Y",
            ">": "Z",
            "2": " "
        },
        "second": {
            ",": ".",
            ":": ",",
            "}": "/",
            "{": "C",
            "]": "8",
            "[": "9",
            ".": "5",
            "_": "E",
            "-": "0",
            "=": "4",
            "+": "3",
            "(": "A",
            ")": "B",
            "&": "S",
            "%": "Q",
            "$": "Z",
            "#": "|",
            "@": "[",
            "!": "]",
            "/": "{",
            "<": "}",
            ">": "?",
            ";": ":",
            "|": ";",
            "*": ">",
            "9": "2"
        }
    }
}